survey_stats/__init__.py
survey_stats/basic_model.py
survey_stats/data_process.py
survey_stats/date.py
survey_stats/functions.py
survey_stats/keyboard.py
survey_stats/shutdown.py
survey_stats/sound.py
survey_stats/test.py
survey_stats/text_to_speech.py
survey_stats/classification/__init__.py
survey_stats/classification/tree_based_regression-last_version.py
survey_stats/classification/tree_based_regression.py
survey_stats/linear_regressions/__init__.py
survey_stats/linear_regressions/ols.py
survey_stats/linear_regressions/ools.py
survey_stats/sklearn/__init__.py
survey_stats/sklearn/logit.py
survey_stats/sklearn/multinominal_logit.py
survey_stats/sklearn/ols.py
survey_stats/statsmodels/__init__.py
survey_stats/statsmodels/logit.py
survey_stats/statsmodels/multinominal_logit.py
survey_stats-1.1.24.dist-info/METADATA
survey_stats-1.1.24.dist-info/WHEEL
survey_stats-1.1.24.dist-info/licenses/LICENSE
survey_stats-1.1.24.dist-info/RECORD
